{
  "ItemData": [
    {
      "Box ID": 0,
      "Index X": 0,
      "Index Y": 0,
      "ItemType": 0,
      "ItemId": 0,
      "InstanceId": 1,
      "Count": 5,
      "CanOverlap": false
    },
    {
      "Box ID": 0,
      "Index X": 1,
      "Index Y": 0,
      "ItemType": 0,
      "ItemId": 1,
      "InstanceId": 2,
      "Count": 5,
      "CanOverlap": false
    },
    {
      "Box ID": 0,
      "Index X": 2,
      "Index Y": 0,
      "ItemType": 0,
      "ItemId": 2,
      "InstanceId": 3,
      "Count": 5,
      "CanOverlap": false
    },
    {
      "Box ID": 0,
      "Index X": 3,
      "Index Y": 0,
      "ItemType": 0,
      "ItemId": 3,
      "InstanceId": 4,
      "Count": 5,
      "CanOverlap": false
    },
    {
      "Box ID": 0,
      "Index X": 4,
      "Index Y": 0,
      "ItemType": 0,
      "ItemId": 4,
      "InstanceId": 4,
      "Count": 5,
      "CanOverlap": false
    },
    {
      "Box ID": 1,
      "Index X": 0,
      "Index Y": 0,
      "ItemType": 0,
      "ItemId": 0,
      "InstanceId": 1,
      "Count": 5,
      "CanOverlap": false
    },
    {
      "Box ID": 1,
      "Index X": 0,
      "Index Y": 1,
      "ItemType": 0,
      "ItemId": 1,
      "InstanceId": 2,
      "Count": 5,
      "CanOverlap": false
    }
  ]
}